cpu/gates/oai21.v

module OAI21 (
    input wire A, B, C,
    output wire Y
  );

  wire w1;
  wire w2;

  or  g1(w1, A, B);
  and g2(w2, w1, C);
  not g3(Y, w2);

endmodule

cpu/testbenches/oai21_tb.v

module oai_tb;

  reg A, B, C;
  wire Y;

  OAI21 dut (
          .A(A),
          .B(B),
          .C(C),
          .Y(Y)
        );

  integer i;

  initial
  begin

    $dumpfile("sim/oai21.vcd");
    $dumpvars(0, oai_tb);

    for (i=0; i < 8; i=i+1)
    begin
      {A, B, C} = i;
      #10;
      $display("A=%b B=%b C=%b Y=%b", A, B, C, Y);
    end

    $finish;

  end

endmodule

cpu/sim/oai21.vcd
$date
	Wed Jul 08 22:06:33 2026
$end
$version
	Icarus Verilog
$end
$timescale
	1s
$end
$scope module oai_tb $end
$var wire 1 ! Y $end
$var reg 1 " A $end
$var reg 1 # B $end
$var reg 1 $ C $end
$var integer 32 % i [31:0] $end
$scope module dut $end
$var wire 1 " A $end
$var wire 1 # B $end
$var wire 1 $ C $end
$var wire 1 ! Y $end
$var wire 1 & w1 $end
$var wire 1 ' w2 $end
$upscope $end
$upscope $end
$enddefinitions $end
$comment Show the parameter values. $end
$dumpall
$end
#0
$dumpvars
0'
0&
b0 %
0$
0#
0"
1!
$end
#10
1$
b1 %
#20
1&
1#
0$
b10 %
#30
0!
1'
1$
b11 %
#40
1!
0'
1"
0#
0$
b100 %
#50
0!
1'
1$
b101 %
#60
1!
0'
1#
0$
b110 %
#70
0!
1'
1$
b111 %
#80
b1000 %
