Standard_Library/aoi/aoi.v

module AOI (
    input wire A, B, C, D,
    output wire Y
);

    wire w1;
    wire w2;
    wire w3;

    and g1(w1, A, B);
    and g2(w2, C, D);
    or  g3(w3, w1, w2);
    not g4(Y, w3);

endmodule

cpu/testbenches/aoi22_tb.v

module aoi_tb;

  reg A, B, C, D;
  wire Y;

  AOI dut (
        .A(A),
        .B(B),
        .C(C),
        .D(D),
        .Y(Y)
      );

  integer i;

  initial
  begin

    $dumpfile("waveform.vcd");
    $dumpvars(0, aoi_tb);

    for (i=0; i < 16; i = i + 1)
    begin
      {A,B,C,D} = i;
      #10;
      $display("A=%b B=%b C=%b D=%b Y=%b", A, B, C, D, Y);
    end

    $finish;

  end

endmodule

Standard_Library/aoi/waveform.vcd
$date
	Wed Jul 08 17:04:11 2026
$end
$version
	Icarus Verilog
$end
$timescale
	1s
$end
$scope module aoi_tb $end
$var wire 1 ! Y $end
$var reg 1 " A $end
$var reg 1 # B $end
$var reg 1 $ C $end
$var reg 1 % D $end
$var integer 32 & i [31:0] $end
$scope module dut $end
$var wire 1 " A $end
$var wire 1 # B $end
$var wire 1 $ C $end
$var wire 1 % D $end
$var wire 1 ! Y $end
$var wire 1 ' w1 $end
$var wire 1 ( w2 $end
$var wire 1 ) w3 $end
$upscope $end
$upscope $end
$enddefinitions $end
$comment Show the parameter values. $end
$dumpall
$end
#0
$dumpvars
0)
0(
0'
b0 &
0%
0$
0#
0"
1!
$end
#10
1%
b1 &
#20
1$
0%
b10 &
#30
0!
1)
1(
1%
b11 &
#40
1!
0)
0(
1#
0$
0%
b100 &
#50
1%
b101 &
#60
1$
0%
b110 &
#70
0!
1)
1(
1%
b111 &
#80
1!
0)
0(
1"
0#
0$
0%
b1000 &
#90
1%
b1001 &
#100
1$
0%
b1010 &
#110
0!
1)
1(
1%
b1011 &
#120
1'
0(
1#
0$
0%
b1100 &
#130
1%
b1101 &
#140
1$
0%
b1110 &
#150
1(
1%
b1111 &
#160
b10000 &
