Verilog-CPU/arithmetic/half_adder.v

// ========================
// Module: half_adder
//
// Computes the sum and carry of two one-bit inputs.
// ========================

module half_adder (
    input  a,
    input  b,
    output sum,
    output cout
);

    assign sum = a ^ b;
    assign cout = a & b;

endmodule

cpu/arithmetic/full_adder.v

`ifdef TEROSHDL
    `include "half_adder.v"
`endif

module full_adder (
    input A,
    input B,
    input Cin,
    output S,
    output Cout
  );

  // Determine S
  wire w1;
  xor xor1(w1, A, B);
  xor xor2(S, w1, Cin);

  // Determine Cout
  wire w2;
  wire w3;
  and and1(w2, w1, Cin);
  and and2(w3, A, B);
  or  or1(Cout, w2, w3);

endmodule

cpu/testbenches/full_adder_tb.v
// Initial template

`timescale 1ns/1ps

module full_adder_tb;

    // Inputs
    reg A;
    reg B;
    reg Cin;

    // Outputs
    wire S;
    wire Cout;

    // Device Under Test
    full_adder dut (
        .A(A),
        .B(B),
        .Cin(Cin),
        .S(S),
        .Cout(Cout)
    );

    integer i;

    initial begin

    `ifdef WAVES
        $dumpfile("sim/full_adder.vcd");
        $dumpvars(0, full_adder_tb);
    `endif

        $display("");
        $display(" A B Cin | S Cout");
        $display("------------------");

        for(i=0; i<8; i=i+1) begin

            {A,B,Cin} = i;

            #1;

            $display(" %b %b  %b  | %b%b",
                Cin,A,B,
                Cout,S
            );

        end

        $finish;

    end

endmodule

Verilog-CPU/sim/full_adder.vcd
$date
	Thu Jul 09 19:30:05 2026
$end
$version
	Icarus Verilog
$end
$timescale
	1s
$end
$scope module full_adder_tb $end
$var wire 1 ! S $end
$var wire 1 " Cout $end
$var reg 1 # A $end
$var reg 1 $ B $end
$var reg 1 % Cin $end
$var integer 32 & i [31:0] $end
$scope module dut $end
$var wire 1 # A $end
$var wire 1 $ B $end
$var wire 1 % Cin $end
$var wire 1 " Cout $end
$var wire 1 ! S $end
$var wire 1 ' w1 $end
$var wire 1 ( w2 $end
$var wire 1 ) w3 $end
$upscope $end
$upscope $end
$enddefinitions $end
$comment Show the parameter values. $end
$dumpall
$end
#0
$dumpvars
0)
0(
0'
b0 &
0%
0$
0#
0"
0!
$end
#10
1!
1%
b1 &
#20
1'
1!
1$
0%
b10 &
#30
1"
0!
1(
1%
b11 &
#40
0"
1!
0(
1#
0$
0%
b100 &
#50
1"
0!
1(
1%
b101 &
#60
0'
1)
0!
0(
1$
0%
b110 &
#70
1!
1%
b111 &
#80
b1000 &
